PlunderGram/LICENSE
PlunderGram/Plunder.py
PlunderGram/__init__.py
PlunderGram/config.ini
PlunderGram/Modules/Boarding.py
PlunderGram/Modules/JollyRoger.py
PlunderGram/Modules/Raid.py
PlunderGram/Modules/Recon.py
PlunderGram/Modules/Spyglass.py
PlunderGram/Modules/__init__.py
PlunderGram/Modules/configread.py
plundergram-1.0.9.dist-info/METADATA
plundergram-1.0.9.dist-info/WHEEL
plundergram-1.0.9.dist-info/entry_points.txt
plundergram-1.0.9.dist-info/top_level.txt
plundergram-1.0.9.dist-info/RECORD
