Metadata-Version: 2.4
Name: plundergram
Version: 1.0.9
Summary: A Telegram OSINT and recon tool (for research use only).
Home-page: https://github.com/kpwnther/plundergram
Author: kpwnther
Author-email: pg.chirpy880@passmail.com
License: Apache-2.0
Keywords: telegram osint recon cli security bot research cyber threat intelligence fraud prevention investigation phishing smishing credential harvesting
Classifier: Programming Language :: Python :: 3
Classifier: License :: OSI Approved :: Apache Software License
Classifier: Operating System :: OS Independent
Requires-Python: >=3.7
Requires-Dist: telethon>=1.28.5
Requires-Dist: requests>=2.25.0
Dynamic: author
Dynamic: author-email
Dynamic: classifier
Dynamic: description
Dynamic: description-content-type
Dynamic: home-page
Dynamic: keywords
Dynamic: license
Dynamic: requires-dist
Dynamic: requires-python
Dynamic: summary
